akedly_client/__init__.py
akedly_client/client.py
akedly_client-0.1.1.dist-info/licenses/LICENSE
akedly_client-0.1.1.dist-info/METADATA
akedly_client-0.1.1.dist-info/WHEEL
akedly_client-0.1.1.dist-info/top_level.txt
akedly_client-0.1.1.dist-info/RECORD
