Metadata-Version: 2.4
Name: akedly-client
Version: 0.1.1
Summary: Unofficial Akedly OTP API Client
Home-page: https://github.com/ahmeddelattarr/Akedly_Client
Author: ahmed elattar
Author-email: ahmeddelattarr@outlook.com
Classifier: Programming Language :: Python :: 3
Classifier: License :: OSI Approved :: MIT License
Classifier: Operating System :: OS Independent
Requires-Python: >=3.7
License-File: LICENSE
Requires-Dist: requests
Requires-Dist: python-dotenv
Dynamic: author
Dynamic: author-email
Dynamic: classifier
Dynamic: description
Dynamic: description-content-type
Dynamic: home-page
Dynamic: license-file
Dynamic: requires-dist
Dynamic: requires-python
Dynamic: summary
